{
    "mission_items": [
        {
            "seq": 0,
            "frame": 0,
            "command": 16,
            "current": 1,
            "autocontinue": 1,
            "x": 46.134561,
            "y": 13.277491,
            "z": 0.08,
            "p1": 0.0,
            "p2": 0.0,
            "p3": 0.0,
            "p4": 0.0
        },
        {
            "seq": 1,
            "frame": 3,
            "command": 16,
            "current": 0,
            "autocontinue": 1,
            "x": 46.134627,
            "y": 13.278365,
            "z": 20.0,
            "p1": 0.0,
            "p2": 0.0,
            "p3": 0.0,
            "p4": 0.0
        },
        {
            "seq": 2,
            "frame": 3,
            "command": 16,
            "current": 0,
            "autocontinue": 1,
            "x": 46.134649,
            "y": 13.278718,
            "z": 20.0,
            "p1": 0.0,
            "p2": 0.0,
            "p3": 0.0,
            "p4": 0.0
        },
        {
            "seq": 3,
            "frame": 3,
            "command": 16,
            "current": 0,
            "autocontinue": 1,
            "x": 46.134434,
            "y": 13.278775,
            "z": 20.0,
            "p1": 0.0,
            "p2": 0.0,
            "p3": 0.0,
            "p4": 0.0
        },
        {
            "seq": 4,
            "frame": 3,
            "command": 16,
            "current": 0,
            "autocontinue": 1,
            "x": 46.134424,
            "y": 13.278422,
            "z": 20.0,
            "p1": 0.0,
            "p2": 0.0,
            "p3": 0.0,
            "p4": 0.0
        },
        {
            "seq": 5,
            "frame": 3,
            "command": 21,
            "current": 0,
            "autocontinue": 1,
            "x": 46.134624,
            "y": 13.278373,
            "z": 0.0,
            "p1": 0.0,
            "p2": 0.0,
            "p3": 0.0,
            "p4": 0.0
        }
    ]
}